.appveyor.yml
.bumpversion.cfg
.cookiecutterrc
.coveragerc
.editorconfig
.travis.yml
AUTHORS.rst
CHANGELOG.rst
CONTRIBUTING.rst
LICENSE
MANIFEST.in
README.rst
environment.yaml
setup.cfg
setup.py
tox.ini
ci/appveyor-with-compiler.cmd
ci/bootstrap.py
ci/requirements.txt
ci/templates/.appveyor.yml
ci/templates/.travis.yml
docs/authors.rst
docs/changelog.rst
docs/conf.py
docs/contributing.rst
docs/index.rst
docs/installation.rst
docs/readme.rst
docs/requirements.txt
docs/spelling_wordlist.txt
docs/usage.rst
docs/reference/index.rst
docs/reference/torchbio.rst
src/torchbio/__init__.py
src/torchbio/__main__.py
src/torchbio/cli.py
src/torchbio.egg-info/PKG-INFO
src/torchbio.egg-info/SOURCES.txt
src/torchbio.egg-info/dependency_links.txt
src/torchbio.egg-info/entry_points.txt
src/torchbio.egg-info/not-zip-safe
src/torchbio.egg-info/top_level.txt
src/torchbio/seq/__init__.py
src/torchbio/seq/const.py
src/torchbio/seq/core.py
tests/test_torchbio.py