Metadata-Version: 1.2
Name: torchbio
Version: 0.0.0
Summary: Pytorch utilities for bioinformatics.
Home-page: https://github.com/dohlee/python-torchbio
Author: Dohoon Lee
Author-email: dohlee.bioinfo@gmail.com
License: MIT
Project-URL: Documentation, https://python-torchbio.readthedocs.io/
Project-URL: Changelog, https://python-torchbio.readthedocs.io/en/latest/changelog.html
Project-URL: Issue Tracker, https://github.com/dohlee/python-torchbio/issues
Platform: UNKNOWN
Classifier: Development Status :: 5 - Production/Stable
Classifier: Intended Audience :: Developers
Classifier: License :: OSI Approved :: MIT License
Classifier: Operating System :: Unix
Classifier: Operating System :: POSIX
Classifier: Operating System :: Microsoft :: Windows
Classifier: Programming Language :: Python
Classifier: Programming Language :: Python :: 2.7
Classifier: Programming Language :: Python :: 3
Classifier: Programming Language :: Python :: 3.5
Classifier: Programming Language :: Python :: 3.6
Classifier: Programming Language :: Python :: 3.7
Classifier: Programming Language :: Python :: 3.8
Classifier: Programming Language :: Python :: Implementation :: CPython
Classifier: Programming Language :: Python :: Implementation :: PyPy
Classifier: Topic :: Utilities
Requires-Python: >=2.7, !=3.0.*, !=3.1.*, !=3.2.*, !=3.3.*, !=3.4.*
